setup.py
rpi_featureSelection_python_tools/__init__.py
rpi_featureSelection_python_tools/feature_selector.py
rpi_featureSelection_python_tools.egg-info/PKG-INFO
rpi_featureSelection_python_tools.egg-info/SOURCES.txt
rpi_featureSelection_python_tools.egg-info/dependency_links.txt
rpi_featureSelection_python_tools.egg-info/entry_points.txt
rpi_featureSelection_python_tools.egg-info/top_level.txt